Metadata-Version: 2.1
Name: first-packages-21
Version: 0.1.0
Summary: My first Python package
Home-page: 
Author: Volkan
Author-email: volkanr@email.com
License: MIT
Keywords: Hello World
Classifier: Operating System :: OS Independent
Classifier: Development Status :: 5 - Production/Stable
Classifier: Programming Language :: Python :: 3
Classifier: License :: OSI Approved :: MIT License
Classifier: Intended Audience :: Education
Requires-Python: >=3.6
